leaky/__init__.py
leaky/__init__.pyi
leaky/_cpp_leaky.cp313-win_amd64.pyd
leaky/_version.py
leaky/leaky_pybind_test.py
leaky/twirling.py
leaky/twirling_test.py
leakysim-0.4.0.dist-info/licenses/LICENSE
leakysim-0.4.0.dist-info/METADATA
leakysim-0.4.0.dist-info/WHEEL
leakysim-0.4.0.dist-info/top_level.txt
leakysim-0.4.0.dist-info/RECORD
