Metadata-Version: 2.4
Name: leakysim
Version: 0.4.0
Summary: An implementation of Google's Pauli+ simulator.
Home-page: https://github.com/inmzhang/leaky
Author: Yiming Zhang
Requires-Python: >=3.9
License-File: LICENSE
Requires-Dist: stim==1.15
Provides-Extra: test
Requires-Dist: pytest>=6.0; extra == "test"
Dynamic: author
Dynamic: description
Dynamic: description-content-type
Dynamic: home-page
Dynamic: license-file
Dynamic: provides-extra
Dynamic: requires-dist
Dynamic: requires-python
Dynamic: summary
